snakeySnake/__init__.py
snakeySnake/__main__.py
snakeySnake/button.py
snakeySnake/context.py
snakeySnake/controlScreen.py
snakeySnake/enums.py
snakeySnake/game.py
snakeySnake/gameOverScreen.py
snakeySnake/gameScreen.py
snakeySnake/scoreBoardScreen.py
snakeySnake/scoreboard.py
snakeySnake/screen.py
snakeySnake/snake.py
snakeySnake/snakeDesignScreen.py
snakeySnake/startScreen.py
snakeySnake/data/apple.png
snakeySnake/data/colour_wheel.png
snakeySnake-0.1.1.dist-info/LICENSE
snakeySnake-0.1.1.dist-info/METADATA
snakeySnake-0.1.1.dist-info/WHEEL
snakeySnake-0.1.1.dist-info/entry_points.txt
snakeySnake-0.1.1.dist-info/top_level.txt
snakeySnake-0.1.1.dist-info/RECORD
