Metadata-Version: 2.1
Name: snakeySnake
Version: 0.1.1
Summary: A pygame implementation of the classic snake game
Author-email: Izzy Parfitt <isobelleparfitt@gmail.com>
Project-URL: Homepage, https://github.com/iparfitt/snakeySnake
Project-URL: Bug Tracker, https://github.com/iparfitt/snakeySnake/issues
Classifier: Programming Language :: Python :: 3
Classifier: License :: OSI Approved :: MIT License
Classifier: Operating System :: OS Independent
Requires-Python: >=3.7
License-File: LICENSE
Requires-Dist: pygame ==2.1.3.dev8
Requires-Dist: subprocess32 ; python_version >= "3.7"
